README.rst
setup.py
djehutyslack/__init__.py
djehutyslack/slack.py
djehutyslack.egg-info/PKG-INFO
djehutyslack.egg-info/SOURCES.txt
djehutyslack.egg-info/dependency_links.txt
djehutyslack.egg-info/requires.txt
djehutyslack.egg-info/top_level.txt